.mina/server.toml
satori/server/__init__.py
satori/server/adapter.py
satori/server/connection.py
satori/server/formdata.py
satori/server/model.py
satori/server/route.py
satori/server/utils.py
satori_python_server-0.17.7.dist-info/METADATA
satori_python_server-0.17.7.dist-info/WHEEL
satori_python_server-0.17.7.dist-info/licenses/LICENSE
satori_python_server-0.17.7.dist-info/RECORD
