Metadata-Version: 2.1
Name: satori-python-server
Version: 0.17.7
Summary: Satori Protocol SDK for python, specify server part
Home-page: https://github.com/RF-Tar-Railt/satori-python
Author-Email: RF-Tar-Railt <rf_tar_railt@qq.com>
License: MIT
Classifier: Typing :: Typed
Classifier: Development Status :: 4 - Beta
Classifier: License :: OSI Approved :: MIT License
Classifier: Programming Language :: Python :: 3.8
Classifier: Programming Language :: Python :: 3.9
Classifier: Programming Language :: Python :: 3.10
Classifier: Programming Language :: Python :: 3.11
Classifier: Programming Language :: Python :: 3.12
Classifier: Operating System :: OS Independent
Project-URL: Homepage, https://github.com/RF-Tar-Railt/satori-python
Project-URL: Repository, https://github.com/RF-Tar-Railt/satori-python
Requires-Python: <4.0,>=3.10
Requires-Dist: aiohttp>=3.9.3
Requires-Dist: launart>=0.8.2
Requires-Dist: graia-amnesia[uvicorn]<0.12.0,>=0.11.0
Requires-Dist: starlette>=0.40.0
Requires-Dist: websockets>=15.0.1
Requires-Dist: python-multipart>=0.0.9
Requires-Dist: satori-python-core>=0.17.0
